mpathy/__init__.py
mpathy/apps.py
mpathy/compat.py
mpathy/fields.py
mpathy/models.py
mpathy/operations.py
django_mpathy-0.2.0.dist-info/LICENSE
django_mpathy-0.2.0.dist-info/METADATA
django_mpathy-0.2.0.dist-info/WHEEL
django_mpathy-0.2.0.dist-info/top_level.txt
django_mpathy-0.2.0.dist-info/RECORD
