Metadata-Version: 2.1
Name: django-mpathy
Version: 0.2.0
Summary: Simple hierarchical data using materialised path, in a postgres database.
Home-page: http://github.com/craigds/django-mpathy
Author: Craig de Stigter
Author-email: craig.ds@gmail.com
License: UNKNOWN
Platform: UNKNOWN
Classifier: Development Status :: 3 - Alpha
Classifier: Topic :: Database
Classifier: Framework :: Django
Classifier: Intended Audience :: Developers
Classifier: License :: OSI Approved :: BSD License
Classifier: Operating System :: OS Independent
Classifier: Programming Language :: Python
Classifier: Programming Language :: Python :: 3
Classifier: Programming Language :: Python :: 3.7
Classifier: Programming Language :: Python :: 3.8
Classifier: Programming Language :: Python :: 3.9
Classifier: Programming Language :: Python :: 3.10
Classifier: Topic :: Utilities
License-File: LICENSE
Requires-Dist: psycopg2 (>=2.7)
Requires-Dist: Django (>=2.2)
